climpy/__init__.py
climpy/metric/__init__.py
climpy/metric/metric.py
climpy/ml_data/__init__.py
climpy/ml_data/data.py
climpy/transform/condition.py
climpy/transform/criterion.py
climpy/transform/event.py
climpy/transform/hazard.py
climpy/transform/link.py
climpy/transform/select.py
climpy/transform/specialized/flood_criterion.py
climpy/transform/utils.py
climpy-0.0.4.dist-info/LICENSE
climpy-0.0.4.dist-info/METADATA
climpy-0.0.4.dist-info/WHEEL
climpy-0.0.4.dist-info/RECORD
