Metadata-Version: 2.1
Name: climpy
Version: 0.0.4
Summary: Tools to analyse climate data for machine learning and event analysis
Home-page: https://github.com/ClimAI/climpy
License: BSD-3-Clause
Keywords: climpy,deep-learning,coincidence-analysis
Author: Mohit Anand
Author-email: mohit@climai.earth
Requires-Python: >=3.9,<3.13
Classifier: License :: OSI Approved :: BSD License
Classifier: Programming Language :: Python :: 3
Classifier: Programming Language :: Python :: 3.9
Classifier: Programming Language :: Python :: 3.10
Classifier: Programming Language :: Python :: 3.11
Requires-Dist: cartopy (>=0.21.1,<0.22.0)
Requires-Dist: geopandas (>=0.13.2,<0.14.0)
Requires-Dist: rioxarray (>=0.14.1,<0.15.0)
Requires-Dist: scipy (>=1.10.1,<2.0.0)
Requires-Dist: xarray (>=2023.5.0,<2024.0.0)
Project-URL: Repository, https://github.com/ClimAI/climpy
